salalem_utils
