Metadata-Version: 1.0
Name: django-salalem-utils
Version: 0.1.2.2.1.4
Summary: Salalem Django Utilities and Extensions
Home-page: https://github.com/salalem/django-salalem_utils/
Author: Firas Al Kafri
Author-email: firas.alkafri@gmail.com
License: GPLv2
Platform: UNKNOWN
